optimizer/__init__.py
optimizer/compressor.py
optimizer/retriever_wrapper.py
optimizer/scorer.py
optimizer/selector.py
optimizer/token_utils.py
optimizer_rag-0.1.2.dist-info/METADATA
optimizer_rag-0.1.2.dist-info/WHEEL
optimizer_rag-0.1.2.dist-info/top_level.txt
optimizer_rag-0.1.2.dist-info/RECORD
