Metadata-Version: 2.4
Name: optimizer-rag
Version: 0.1.2
Summary: A document compression and optimization library using Groq LLMs and LangChain
Author: Mihir Kapile
Author-email: mihirkapile@gmail.com
Classifier: Programming Language :: Python :: 3
Classifier: Operating System :: OS Independent
Requires-Python: >=3.8
Requires-Dist: langchain>=0.1.16
Requires-Dist: groq
Requires-Dist: tiktoken
Requires-Dist: numpy
Requires-Dist: scikit-learn
Requires-Dist: sentence-transformers
Requires-Dist: streamlit
Requires-Dist: python-dotenv
Dynamic: author
Dynamic: author-email
Dynamic: classifier
Dynamic: description
Dynamic: description-content-type
Dynamic: requires-dist
Dynamic: requires-python
Dynamic: summary
